{
    "description": "",
    "tags": [],
    "size": {
        "height": 800,
        "width": 1422
    },
    "objects": [
        {
            "id": 511624561,
            "classId": 1846335,
            "description": "",
            "geometryType": "polygon",
            "labelerLogin": "anna@supervise.ly",
            "createdAt": "2020-09-11T08:57:16.643Z",
            "updatedAt": "2020-09-11T08:57:16.643Z",
            "tags": [],
            "classTitle": "person_poly",
            "points": {
                "exterior": [
                    [
                        569,
                        480
                    ],
                    [
                        572,
                        493
                    ],
                    [
                        574,
                        506
                    ],
                    [
                        577,
                        528
                    ],
                    [
                        580,
                        546
                    ],
                    [
                        586,
                        572
                    ],
                    [
                        591,
                        585
                    ],
                    [
                        596,
                        621
                    ],
                    [
                        599,
                        650
                    ],
                    [
                        599,
                        660
                    ],
                    [
                        600,
                        667
                    ],
                    [
                        601,
                        680
                    ],
                    [
                        602,
                        690
                    ],
                    [
                        601,
                        705
                    ],
                    [
                        599,
                        714
                    ],
                    [
                        594,
                        723
                    ],
                    [
                        593,
                        732
                    ],
                    [
                        596,
                        738
                    ],
                    [
                        611,
                        738
                    ],
                    [
                        624,
                        737
                    ],
                    [
                        631,
                        731
                    ],
                    [
                        636,
                        728
                    ],
                    [
                        637,
                        723
                    ],
                    [
                        635,
                        702
                    ],
                    [
                        636,
                        694
                    ],
                    [
                        637,
                        686
                    ],
                    [
                        634,
                        680
                    ],
                    [
                        631,
                        677
                    ],
                    [
                        630,
                        671
                    ],
                    [
                        631,
                        664
                    ],
                    [
                        630,
                        659
                    ],
                    [
                        628,
                        654
                    ],
                    [
                        629,
                        640
                    ],
                    [
                        631,
                        623
                    ],
                    [
                        630,
                        597
                    ],
                    [
                        625,
                        569
                    ],
                    [
                        621,
                        551
                    ],
                    [
                        620,
                        527
                    ],
                    [
                        619,
                        499
                    ],
                    [
                        628,
                        497
                    ],
                    [
                        634,
                        492
                    ],
                    [
                        639,
                        489
                    ],
                    [
                        640,
                        468
                    ],
                    [
                        641,
                        458
                    ],
                    [
                        638,
                        443
                    ],
                    [
                        640,
                        441
                    ],
                    [
                        640,
                        436
                    ],
                    [
                        638,
                        431
                    ],
                    [
                        635,
                        398
                    ],
                    [
                        634,
                        384
                    ],
                    [
                        629,
                        371
                    ],
                    [
                        628,
                        351
                    ],
                    [
                        629,
                        340
                    ],
                    [
                        635,
                        337
                    ],
                    [
                        637,
                        333
                    ],
                    [
                        631,
                        312
                    ],
                    [
                        633,
                        306
                    ],
                    [
                        628,
                        283
                    ],
                    [
                        625,
                        261
                    ],
                    [
                        622,
                        228
                    ],
                    [
                        617,
                        191
                    ],
                    [
                        613,
                        184
                    ],
                    [
                        608,
                        178
                    ],
                    [
                        599,
                        174
                    ],
                    [
                        587,
                        171
                    ],
                    [
                        572,
                        171
                    ],
                    [
                        561,
                        176
                    ],
                    [
                        553,
                        184
                    ],
                    [
                        547,
                        201
                    ],
                    [
                        542,
                        227
                    ],
                    [
                        538,
                        248
                    ],
                    [
                        533,
                        250
                    ],
                    [
                        524,
                        249
                    ],
                    [
                        515,
                        249
                    ],
                    [
                        505,
                        255
                    ],
                    [
                        497,
                        266
                    ],
                    [
                        485,
                        281
                    ],
                    [
                        481,
                        285
                    ],
                    [
                        489,
                        293
                    ],
                    [
                        483,
                        316
                    ],
                    [
                        479,
                        343
                    ],
                    [
                        477,
                        352
                    ],
                    [
                        482,
                        358
                    ],
                    [
                        488,
                        372
                    ],
                    [
                        503,
                        390
                    ],
                    [
                        503,
                        402
                    ],
                    [
                        501,
                        418
                    ],
                    [
                        503,
                        436
                    ],
                    [
                        506,
                        446
                    ],
                    [
                        505,
                        461
                    ],
                    [
                        503,
                        490
                    ],
                    [
                        504,
                        530
                    ],
                    [
                        501,
                        558
                    ],
                    [
                        495,
                        597
                    ],
                    [
                        494,
                        611
                    ],
                    [
                        490,
                        627
                    ],
                    [
                        489,
                        644
                    ],
                    [
                        484,
                        656
                    ],
                    [
                        487,
                        669
                    ],
                    [
                        485,
                        678
                    ],
                    [
                        487,
                        692
                    ],
                    [
                        485,
                        700
                    ],
                    [
                        483,
                        710
                    ],
                    [
                        477,
                        723
                    ],
                    [
                        470,
                        737
                    ],
                    [
                        468,
                        744
                    ],
                    [
                        471,
                        749
                    ],
                    [
                        473,
                        754
                    ],
                    [
                        480,
                        754
                    ],
                    [
                        500,
                        752
                    ],
                    [
                        502,
                        745
                    ],
                    [
                        505,
                        744
                    ],
                    [
                        510,
                        745
                    ],
                    [
                        511,
                        729
                    ],
                    [
                        510,
                        720
                    ],
                    [
                        513,
                        714
                    ],
                    [
                        510,
                        711
                    ],
                    [
                        511,
                        701
                    ],
                    [
                        514,
                        696
                    ],
                    [
                        517,
                        691
                    ],
                    [
                        517,
                        682
                    ],
                    [
                        520,
                        677
                    ],
                    [
                        521,
                        672
                    ],
                    [
                        520,
                        663
                    ],
                    [
                        522,
                        657
                    ],
                    [
                        526,
                        638
                    ],
                    [
                        533,
                        600
                    ],
                    [
                        542,
                        568
                    ],
                    [
                        543,
                        557
                    ],
                    [
                        555,
                        510
                    ],
                    [
                        569,
                        480
                    ]
                ],
                "interior": [
                    [
                        [
                            622,
                            468
                        ],
                        [
                            624,
                            453
                        ],
                        [
                            624,
                            445
                        ],
                        [
                            618,
                            429
                        ],
                        [
                            618,
                            438
                        ],
                        [
                            619,
                            456
                        ],
                        [
                            620,
                            473
                        ],
                        [
                            622,
                            468
                        ]
                    ],
                    [
                        [
                            607,
                            396
                        ],
                        [
                            605,
                            383
                        ],
                        [
                            604,
                            366
                        ],
                        [
                            599,
                            340
                        ],
                        [
                            594,
                            346
                        ],
                        [
                            594,
                            353
                        ],
                        [
                            594,
                            358
                        ],
                        [
                            597,
                            362
                        ],
                        [
                            597,
                            366
                        ],
                        [
                            596,
                            369
                        ],
                        [
                            598,
                            374
                        ],
                        [
                            600,
                            384
                        ],
                        [
                            605,
                            392
                        ],
                        [
                            607,
                            396
                        ]
                    ]
                ]
            }
        }
    ]
}