{
    "description": "",
    "tags": [],
    "size": {
        "height": 800,
        "width": 1200
    },
    "objects": [
        {
            "id": 511624824,
            "classId": 1846335,
            "description": "",
            "geometryType": "polygon",
            "labelerLogin": "anna@supervise.ly",
            "createdAt": "2020-09-11T08:57:16.643Z",
            "updatedAt": "2020-09-11T08:57:16.643Z",
            "tags": [],
            "classTitle": "person_poly",
            "points": {
                "exterior": [
                    [
                        364,
                        799
                    ],
                    [
                        478,
                        799
                    ],
                    [
                        486,
                        785
                    ],
                    [
                        496,
                        769
                    ],
                    [
                        500,
                        759
                    ],
                    [
                        509,
                        751
                    ],
                    [
                        516,
                        730
                    ],
                    [
                        526,
                        711
                    ],
                    [
                        522,
                        724
                    ],
                    [
                        526,
                        738
                    ],
                    [
                        534,
                        749
                    ],
                    [
                        547,
                        762
                    ],
                    [
                        551,
                        782
                    ],
                    [
                        558,
                        799
                    ],
                    [
                        949,
                        799
                    ],
                    [
                        945,
                        769
                    ],
                    [
                        947,
                        748
                    ],
                    [
                        943,
                        670
                    ],
                    [
                        945,
                        644
                    ],
                    [
                        950,
                        623
                    ],
                    [
                        947,
                        595
                    ],
                    [
                        937,
                        564
                    ],
                    [
                        930,
                        542
                    ],
                    [
                        918,
                        522
                    ],
                    [
                        897,
                        510
                    ],
                    [
                        872,
                        496
                    ],
                    [
                        827,
                        447
                    ],
                    [
                        819,
                        420
                    ],
                    [
                        798,
                        378
                    ],
                    [
                        779,
                        317
                    ],
                    [
                        766,
                        278
                    ],
                    [
                        755,
                        240
                    ],
                    [
                        734,
                        207
                    ],
                    [
                        709,
                        193
                    ],
                    [
                        672,
                        183
                    ],
                    [
                        658,
                        182
                    ],
                    [
                        637,
                        189
                    ],
                    [
                        614,
                        197
                    ],
                    [
                        591,
                        209
                    ],
                    [
                        572,
                        222
                    ],
                    [
                        553,
                        238
                    ],
                    [
                        540,
                        268
                    ],
                    [
                        536,
                        292
                    ],
                    [
                        527,
                        311
                    ],
                    [
                        518,
                        351
                    ],
                    [
                        524,
                        371
                    ],
                    [
                        517,
                        375
                    ],
                    [
                        499,
                        397
                    ],
                    [
                        490,
                        408
                    ],
                    [
                        479,
                        417
                    ],
                    [
                        474,
                        421
                    ],
                    [
                        475,
                        436
                    ],
                    [
                        476,
                        469
                    ],
                    [
                        476,
                        486
                    ],
                    [
                        464,
                        523
                    ],
                    [
                        447,
                        559
                    ],
                    [
                        421,
                        610
                    ],
                    [
                        403,
                        635
                    ],
                    [
                        396,
                        657
                    ],
                    [
                        384,
                        672
                    ],
                    [
                        381,
                        695
                    ],
                    [
                        369,
                        719
                    ],
                    [
                        366,
                        737
                    ],
                    [
                        362,
                        747
                    ],
                    [
                        359,
                        777
                    ],
                    [
                        364,
                        799
                    ]
                ],
                "interior": []
            }
        }
    ]
}